ae_app/__init__.py
ae_app/admin.py
ae_app/apps.py
ae_app/models.py
ae_app/tests.py
ae_app/views.py
ae_app/migrations/__init__.py
meta_ae/__init__.py
meta_ae/action_items.py
meta_ae/admin_site.py
meta_ae/apps.py
meta_ae/choices.py
meta_ae/constants.py
meta_ae/list_data.py
meta_ae/mommy_recipes.py
meta_ae/urls.py
meta_ae/admin/__init__.py
meta_ae/admin/ae_followup_admin.py
meta_ae/admin/ae_initial_admin.py
meta_ae/admin/ae_susar_admin.py
meta_ae/admin/ae_tmg_admin.py
meta_ae/admin/death_report_admin.py
meta_ae/admin/death_report_tmg_admin.py
meta_ae/admin/death_report_tmg_second_admin.py
meta_ae/forms/__init__.py
meta_ae/forms/ae_followup_form.py
meta_ae/forms/ae_initial_form.py
meta_ae/forms/ae_susar_form.py
meta_ae/forms/ae_tmg_form.py
meta_ae/forms/death_report_form.py
meta_ae/forms/death_report_tmg_form.py
meta_ae/forms/death_report_tmg_second_form.py
meta_ae/migrations/0001_initial.py
meta_ae/migrations/0002_auto_20191024_1000.py
meta_ae/migrations/0003_auto_20191102_0033.py
meta_ae/migrations/0004_auto_20191114_0821.py
meta_ae/migrations/__init__.py
meta_ae/models/__init__.py
meta_ae/models/ae_followup.py
meta_ae/models/ae_initial.py
meta_ae/models/ae_susar.py
meta_ae/models/ae_tmg.py
meta_ae/models/death_report.py
meta_ae/models/death_report_tmg.py
meta_ae/models/death_report_tmg_second.py
meta_ae/models/managers.py
meta_ae/models/model_mixins.py
meta_ae/pdf_reports/__init__.py
meta_ae/pdf_reports/ae_report.py
meta_ae/pdf_reports/death_report.py
meta_ae/pdf_reports/meta_pdf_report_mixin.py
meta_ae/templates/meta_ae/bootstrap3/ae_initial_description.html
meta_ae/templatetags/__init__.py
meta_ae/templatetags/meta_ae_extras.py
meta_ae/tests/__init__.py
meta_ae/tests/test_actions.py
meta_ae/tests/urls.py
meta_ae-0.1.15.dist-info/AUTHORS
meta_ae-0.1.15.dist-info/LICENSE
meta_ae-0.1.15.dist-info/METADATA
meta_ae-0.1.15.dist-info/WHEEL
meta_ae-0.1.15.dist-info/top_level.txt
meta_ae-0.1.15.dist-info/RECORD
